group27_lab6_part1/reg_file.v
/* Lab 5 : Part 4 Flow Control Instructions - reg file
   Group 27
*/

///////////////////////////    register file      ///////////////////////////////////
module register_file(DATAINIn, Output_1, Output_2, DATAINInAddress, OutputAddress_1, OutputAddress_2, WRITE, CLK, RESET);

    reg [7:0] Register[0:7]; //8, 8 bit registers inside

    //declaration of inputs and ouputs
    input [7:0] DATAINIn;
    input [2:0] OutputAddress_1, OutputAddress_2, DATAINInAddress;
    input CLK, RESET, WRITE;
    output [7:0] Output_1, Output_2;

    integer i;

    //read asynchronously and load values into Output_1 and Output_2 
    assign #2 Output_1 = Register[OutputAddress_1];
    assign #2 Output_2 = Register[OutputAddress_2];

    //always block only teriggerd in the positive edge of clock
    always@(posedge CLK)
    begin
        if(WRITE & !RESET) begin// if write port is set to high and reset is low then IN port is write into register named as DATAINInAddress
           #1 Register[DATAINInAddress] <= DATAINIn;
        end
        if(RESET) begin // if reset is high, all values in registers are written as 0
            #1
            for(i = 0; i < 8; i += 1) begin // make for loop for access each element in an array
                Register[i] = 8'd0;
            end
        end

    end

endmodule
//////////////////////////////////////////////////////////////////////////////////////////////////

group27_lab5_part4/alu.v
/* Lab 5 : Part 4 Flow Control Instructions - ALU
   Group 27
*/


//////////////////////////       ALU          /////////////////////////////////////////////////////////////////
module alu(DATAIN1, DATAIN2, RESULT, SELECT, ZERO);

    //port declaration
    // inputs
    input [7 : 0] DATAIN1, DATAIN2;
    input [2 : 0] SELECT;
    // outputs
    output reg [7 : 0] RESULT;  
    wire [7 : 0] FWD_OUT, ADD_OUT, AND_OUT, OR_OUT; //get outputs from the function modules
    output reg ZERO;

    //instantiate function modules
    FORWARD fwd(DATAIN2, FWD_OUT);
    ADD add(DATAIN1, DATAIN2, ADD_OUT);
    AND And(DATAIN1, DATAIN2, AND_OUT);
    OR Or(DATAIN1, DATAIN2, OR_OUT);

     always@(ADD_OUT) begin
       if(ADD_OUT == 0) ZERO = 1; //set ZERO signal to high if answer of subrtraction is ZERO
      else ZERO = 0; // otherwise set it to low
     end

     //selecting the relevant output result according to the SELECT input
    always @(DATAIN1,DATAIN2,SELECT)
    begin
        case (SELECT)
            3'b000 : assign RESULT = FWD_OUT;   //SELECT 000 -> FORWARD
            3'b001 : assign RESULT = ADD_OUT;  //SELECT 001 -> ADD
            3'b010 : assign RESULT = AND_OUT;  //SELECT 010 -> AND
            3'b011 : assign RESULT = OR_OUT;   //SELECT 011 -> OR
            default: assign RESULT = 8'd0;        
        endcase
        
    end

endmodule

// FORWARD module - for loadi, mov instructions
module FORWARD(DATAIN2, FWD_OUT);

    // port declaration
    input [7 : 0] DATAIN2;
    output [7 : 0] FWD_OUT;

    assign #1 FWD_OUT = DATAIN2; // wait for 1 time unit and assign value of DATAIN2 to FWD_OUT
endmodule


// ADD module - for add, sub instructions
module ADD(DATAIN1, DATAIN2, ADD_OUT);

    // port declaration
    input [7 : 0] DATAIN1;
    input [7 : 0] DATAIN2;
    output [7 : 0] ADD_OUT;

    assign #2 ADD_OUT = DATAIN1 + DATAIN2; // wait for 2 time unit and assign sum of DATAIN1 and DATAIN2 to ADD_OUT

endmodule

// AND module - for and instruction
module AND(DATAIN1, DATAIN2, AND_OUT);

    // port declaration
    input [7 : 0] DATAIN1;
    input [7 : 0] DATAIN2;
    output [7 : 0] AND_OUT;

    assign #1 AND_OUT = DATAIN1 & DATAIN2; // wait for 1 time unit and assign AND of DATAIN1 and DATAIN2 to AND_OUT

endmodule

// OR module - for or instruction
module OR(DATAIN1, DATAIN2, OR_OUT);

    // port declaration
    input [7 : 0] DATAIN1;
    input [7 : 0] DATAIN2;
    output [7 : 0] OR_OUT;

    assign #1 OR_OUT = DATAIN1 | DATAIN2; // wait for 1 time unit and assign OR of DATAIN1 and DATAIN2 to OR_OUT

endmodule
///////////////////////////////////////////////////////////////////////////////////////////////////

group27_lab5_part4/lab5part4.v
/* Lab 5 : Part 4 Flow Control Instructions
   Group 27
*/

`include "alu.v"
`include "reg_file.v"

/////////////////////////////////////////////////// CPU_tb/////////////////////////////////////////////////////////////////

module cpu_tb;

    reg CLK, RESET;
    wire [31:0] PC;
    reg [31:0] INSTRUCTION;
    integer i;
    
    /* 
    ------------------------
     SIMPLE INSTRUCTION MEM
    ------------------------
    */
    
    // TODO: Initialize an array of registers (8x1024) named 'instr_mem' to be used as instruction memory
    reg [7:0] instr_mem[0:1023];
    
    // TODO: Create combinational logic to support CPU instruction fetching, given the Program Counter(PC) value 
    //       (make sure you include the delay for instruction fetching here)
    always @(PC) begin
        #2
        INSTRUCTION = {instr_mem[PC+3], instr_mem[PC+2], instr_mem[PC+1], instr_mem[PC]};
    end
    
    initial
    begin
        // Initialize instruction memory with the set of instructions you need execute on CPU
        
        // METHOD 1: manually loading instructions to instr_mem
        //{instr_mem[10'd3], instr_mem[10'd2], instr_mem[10'd1], instr_mem[10'd0]} = 32'b00000000000001000000000000000101;
        //{instr_mem[10'd7], instr_mem[10'd6], instr_mem[10'd5], instr_mem[10'd4]} = 32'b00000000000000100000000000001001;
        //{instr_mem[10'd11], instr_mem[10'd10], instr_mem[10'd9], instr_mem[10'd8]} = 32'b00000010000001100000010000000010;
        
        // METHOD 2: loading instr_mem content from instr_mem.mem file
       $readmemb("instr_mem.mem", instr_mem);
    end
    
    /* 
    -----
     CPU
    -----
    */
    cpu mycpu(PC, INSTRUCTION, CLK, RESET);

    initial
    begin
    
        // generate files needed to plot the waveform using GTKWave
        $dumpfile("cpu_wavedata.vcd");
		$dumpvars(0, cpu_tb);

        for(i=0;i<8;i=i+1)
        begin
            $dumpvars(1,cpu_tb.mycpu.r1.Register[i]);
        end 
        
        CLK = 1'b0;
        RESET = 1'b0;
        
        // TODO: Reset the CPU (by giving a pulse to RESET signal) to start the program execution
        #2
        RESET = 1'b1;

        #4
        RESET= 1'b0;
        
        // finish simulation after some time
        #200
        $finish;
        
    end
    
    // clock signal generation
    always
        #4 CLK = ~CLK;
        
endmodule

//////////////////////////////////////////////////   CPU     ////////////////////////////////////////////////////////////////
module cpu(PC, INSTRUCTION, CLK, RESET);
    output reg [31:0] PC;
    input [31:0] INSTRUCTION;
    input CLK, RESET;

    wire [7:0] OUT1, OUT2, OUT3, OUT4, NEGATIVE,RESULT;
    reg [2:0] WRITE_ADRS,READ_ADRS1, READ_ADRS2, SEL;
    reg [7:0] BRANCH;
    reg WRITE , isNEGATIVE, isIMMEDIATE, isBRANCH, isJUMP;

    wire [31:0] NEXT_INS,EXTENDED, SHIFTED, BRANCHto, PCbranch, PCNEXT;
    wire ZERO,AND_OUT;


    //instantiate all sub modules
    alu a1(OUT1, OUT4, RESULT, SEL, ZERO);
    register_file r1(RESULT, OUT1, OUT2, WRITE_ADRS,READ_ADRS1, READ_ADRS2, WRITE, CLK, RESET);
    PC_adder add(PC, NEXT_INS); 
    twosCompliment t1(OUT2, NEGATIVE); // get 2's compliment
    MUX isNeg(NEGATIVE, OUT2, OUT3, isNEGATIVE); //select negative value for sub instruction and positive value for add instruction
    MUX isIMM(INSTRUCTION[7:0], OUT3, OUT4, isIMMEDIATE); //select immediate value or register value 

    AND2 and_gate(ZERO, isBRANCH, AND_OUT); //get the AND value of Zero and isBranch to do beq instruction
    PC_MUX m1(BRANCHto, NEXT_INS, PCbranch, AND_OUT); // select next pc value according to AND output
    Sign_extend s1(INSTRUCTION[23:16], EXTENDED); // sign extend given value to 32 bit before find the offset
    shift shift_2(EXTENDED, SHIFTED); // multiply the sign extended value by 4.(shift 2)
    Branch_ADD brAdd(NEXT_INS, SHIFTED, BRANCHto); // calculate the new PC value using shifted value
    PC_MUX m2(BRANCHto, PCbranch, PCNEXT, isJUMP); // select jump or branch to decide next PC value

    always @(posedge CLK) begin
        if (RESET == 1'b1) 
		begin
			#1
			PC = 0;		 //When  the reset is 1 PC should be 0
		end
        else #1 PC = PCNEXT;         //PC update (delay 1 unit)
            
    end

    always @(INSTRUCTION) begin

        //assign instuction to reg_file inputs
        WRITE_ADRS = INSTRUCTION[18:16];
        READ_ADRS1 = INSTRUCTION[10:8];
        READ_ADRS2 = INSTRUCTION[2:0];

        //Control Unit
        //check opcode and decode
        #1
        case(INSTRUCTION[31:24]) 
            8'd0 : //loadi instruction
                begin
                    WRITE = 1;          //enable write 
                    isNEGATIVE = 1'b0;  //no need for subtraction
                    isIMMEDIATE = 1'b1; //loadi instruction contain immediate value
                    SEL = 3'b000;       //select alu FORWARD operation
                    isJUMP = 1'b0;      //no instruction jumps
                    isBRANCH = 1'b0;    //no branchings

                end
            8'd1 : //mov instruction
                begin
                    WRITE = 1;          //enable write
                    isNEGATIVE = 1'b0;  //no need for subtraction
                    isIMMEDIATE = 1'b0; //no immediate value
                    SEL = 3'b000;       //select alu FORWARD operation
                    isJUMP = 1'b0;
                    isBRANCH = 1'b0;

                end
            8'd2 : //add instruction 
                begin
                    WRITE = 1;          //enable write
                    isNEGATIVE = 1'b0;  //no need for subtraction
                    isIMMEDIATE = 1'b0; //no immediate value
                    SEL = 3'b001;       //select alu ADD operation
                    isJUMP = 1'b0;
                    isBRANCH = 1'b0;
                    
                end
            8'd3 : //sub instruction
                begin
                    WRITE = 1;          //enable write
                    isNEGATIVE = 1'b1;  //need to substract value so isNegative is high
                    isIMMEDIATE = 1'b0; //no immediate value
                    SEL = 3'b001;       //select alu ADD operation
                    isJUMP = 1'b0;
                    isBRANCH = 1'b0;
                    
                end
            8'd4 : //and instruction 
                begin
                    WRITE = 1;           //enable write
                    isNEGATIVE = 1'b0;   //no need for subtraction
                    isIMMEDIATE = 1'b0;  //no immediate value
                    SEL = 3'b010;        //select alu AND operation
                    isJUMP = 1'b0;
                    isBRANCH = 1'b0;
                    
                end
            8'd5 : //or instruction
                begin
                    WRITE = 1;           //enable write
                    isNEGATIVE = 1'b0;   //no need for subtraction
                    isIMMEDIATE = 1'b0;  //no immediate value
                    SEL = 3'b011;        //select alu OR operation 
                    isJUMP = 1'b0;
                    isBRANCH = 1'b0;
                    
                end
            8'd6 : //jump instruction
                begin
                    WRITE = 0;          // not writing to the register
                    isNEGATIVE = 1'b0;  //no need for subtraction
                    isIMMEDIATE = 1'b0; // no immidiate value
                    SEL = 3'b000;       //no need alu operation
                    isJUMP = 1'b1;      // jump signal is high
                    isBRANCH = 1'b0;    // no branchings
                    
                end
            8'd7 : //branch instruction
                begin
                    WRITE = 0;          // not writing to the register 
                    isNEGATIVE = 1'b1;  // get negative value for subtraction
                    isIMMEDIATE = 1'b0; // dont need immidiate values
                    isJUMP = 1'b0;      // jump is low
                    isBRANCH = 1'b1;    // branch signal is high
                    SEL = 3'b001;       //select alu ADD operation
                    
                end
            
            
        endcase
    
    end

    

endmodule

/////////////////////////////////////////

 //module for 2's compliment
module twosCompliment(DATAIN, OUT);
   //declare input and output
   input [7:0] DATAIN;
   output [7:0] OUT;
   assign #1 OUT = ~DATAIN + 1;  //get 2's compliment by negating and adding 1
endmodule

//module for the selector MUX
module MUX(IN1, IN2, OUT, SELECT);
    input [7:0] IN1, IN2;
    input SELECT;
    output reg [7:0] OUT;

    always@(*) begin
        case(SELECT)
            1'b1: OUT <= IN1;
            1'b0: OUT <= IN2;
            default: OUT <= 8'd0;
        endcase
    end
endmodule

// dedicated adder for PC 
module PC_adder(IN, NEXT_INS);
    input [31:0] IN; // input address (current instruction)
    output [31:0] NEXT_INS; // output address (NEXT_INS instruction)

    assign #1 NEXT_INS = IN + 32'd4; // increment the PC value by 4 (delay 1 time unit)
  
endmodule

// AND gate
module AND2(INPUT1,INPUT2,OUTPUT);
    input INPUT1,INPUT2;
    output OUTPUT;

    and(OUTPUT,INPUT1,INPUT2); 
endmodule

///////////////////////////////////////
//module for Add offset value to PC value for branching
module Branch_ADD(pcNext, offset, out);
    input [31:0] pcNext, offset;
    output [31:0] out;

    assign #2 out = pcNext + offset;

endmodule

//module for sign extend
module Sign_extend(IN, OUT);
    input [7:0] IN; //8 bit input
    output [31:0] OUT; //32 bit output

    assign OUT[7:0] = IN[7:0];
    assign OUT[31:8] = {24{IN[7]}};
    initial begin
    end
endmodule

//module for shift 2 times
module shift(IN, OUT);
    input signed[31:0] IN;
    output signed[31:0] OUT;

    assign OUT = IN << 2; // multiply by 4

endmodule

//mux module for select right pc value
module PC_MUX(IN1, IN2, OUT, SELECT);
    input [31:0] IN1, IN2;
    input SELECT;
    output reg [31:0] OUT;

    always@(*) begin
        case(SELECT)
            1'b1: OUT <= IN1;
            1'b0: OUT <= IN2;
        endcase
    end
endmodule

group27_lab5_part4/cpu_wavedata.vcd
$date
	Wed May 31 10:35:57 2023
$end
$version
	Icarus Verilog
$end
$timescale
	1s
$end
$scope module cpu_tb $end
$var wire 32 ! PC [31:0] $end
$var reg 1 " CLK $end
$var reg 32 # INSTRUCTION [31:0] $end
$var reg 1 $ RESET $end
$var integer 32 % i [31:0] $end
$scope module mycpu $end
$var wire 1 " CLK $end
$var wire 32 & INSTRUCTION [31:0] $end
$var wire 1 $ RESET $end
$var wire 1 ' ZERO $end
$var wire 32 ( SHIFTED [31:0] $end
$var wire 8 ) RESULT [7:0] $end
$var wire 32 * PCbranch [31:0] $end
$var wire 32 + PCNEXT [31:0] $end
$var wire 8 , OUT4 [7:0] $end
$var wire 8 - OUT3 [7:0] $end
$var wire 8 . OUT2 [7:0] $end
$var wire 8 / OUT1 [7:0] $end
$var wire 32 0 NEXT_INS [31:0] $end
$var wire 8 1 NEGATIVE [7:0] $end
$var wire 32 2 EXTENDED [31:0] $end
$var wire 32 3 BRANCHto [31:0] $end
$var wire 1 4 AND_OUT $end
$var reg 32 5 PC [31:0] $end
$var reg 3 6 READ_ADRS1 [2:0] $end
$var reg 3 7 READ_ADRS2 [2:0] $end
$var reg 3 8 SEL [2:0] $end
$var reg 1 9 WRITE $end
$var reg 3 : WRITE_ADRS [2:0] $end
$var reg 1 ; isBRANCH $end
$var reg 1 < isIMMEDIATE $end
$var reg 1 = isJUMP $end
$var reg 1 > isNEGATIVE $end
$scope module a1 $end
$var wire 3 ? SELECT [2:0] $end
$var wire 8 @ OR_OUT [7:0] $end
$var wire 8 A FWD_OUT [7:0] $end
$var wire 8 B DATAIN2 [7:0] $end
$var wire 8 C DATAIN1 [7:0] $end
$var wire 8 D AND_OUT [7:0] $end
$var wire 8 E ADD_OUT [7:0] $end
$var reg 8 F RESULT [7:0] $end
$var reg 1 ' ZERO $end
$scope module And $end
$var wire 8 G AND_OUT [7:0] $end
$var wire 8 H DATAIN2 [7:0] $end
$var wire 8 I DATAIN1 [7:0] $end
$upscope $end
$scope module Or $end
$var wire 8 J OR_OUT [7:0] $end
$var wire 8 K DATAIN2 [7:0] $end
$var wire 8 L DATAIN1 [7:0] $end
$upscope $end
$scope module add $end
$var wire 8 M DATAIN2 [7:0] $end
$var wire 8 N DATAIN1 [7:0] $end
$var wire 8 O ADD_OUT [7:0] $end
$upscope $end
$scope module fwd $end
$var wire 8 P FWD_OUT [7:0] $end
$var wire 8 Q DATAIN2 [7:0] $end
$upscope $end
$upscope $end
$scope module add $end
$var wire 32 R IN [31:0] $end
$var wire 32 S NEXT_INS [31:0] $end
$upscope $end
$scope module and_gate $end
$var wire 1 ' INPUT1 $end
$var wire 1 ; INPUT2 $end
$var wire 1 4 OUTPUT $end
$upscope $end
$scope module brAdd $end
$var wire 32 T pcNext [31:0] $end
$var wire 32 U out [31:0] $end
$var wire 32 V offset [31:0] $end
$upscope $end
$scope module isIMM $end
$var wire 8 W IN1 [7:0] $end
$var wire 1 < SELECT $end
$var wire 8 X IN2 [7:0] $end
$var reg 8 Y OUT [7:0] $end
$upscope $end
$scope module isNeg $end
$var wire 1 > SELECT $end
$var wire 8 Z IN2 [7:0] $end
$var wire 8 [ IN1 [7:0] $end
$var reg 8 \ OUT [7:0] $end
$upscope $end
$scope module m1 $end
$var wire 32 ] IN1 [31:0] $end
$var wire 32 ^ IN2 [31:0] $end
$var wire 1 4 SELECT $end
$var reg 32 _ OUT [31:0] $end
$upscope $end
$scope module m2 $end
$var wire 32 ` IN1 [31:0] $end
$var wire 32 a IN2 [31:0] $end
$var wire 1 = SELECT $end
$var reg 32 b OUT [31:0] $end
$upscope $end
$scope module r1 $end
$var wire 1 " CLK $end
$var wire 8 c DATAINIn [7:0] $end
$var wire 3 d DATAINInAddress [2:0] $end
$var wire 3 e OutputAddress_1 [2:0] $end
$var wire 3 f OutputAddress_2 [2:0] $end
$var wire 8 g Output_1 [7:0] $end
$var wire 8 h Output_2 [7:0] $end
$var wire 1 $ RESET $end
$var wire 1 9 WRITE $end
$var integer 32 i i [31:0] $end
$upscope $end
$scope module s1 $end
$var wire 8 j IN [7:0] $end
$var wire 32 k OUT [31:0] $end
$upscope $end
$scope module shift_2 $end
$var wire 32 l IN [31:0] $end
$var wire 32 m OUT [31:0] $end
$upscope $end
$scope module t1 $end
$var wire 8 n DATAIN [7:0] $end
$var wire 8 o OUT [7:0] $end
$upscope $end
$upscope $end
$upscope $end
$scope module cpu_tb $end
$scope module mycpu $end
$scope module r1 $end
$var reg 8 p \Register[0] [7:0] $end
$upscope $end
$upscope $end
$upscope $end
$scope module cpu_tb $end
$scope module mycpu $end
$scope module r1 $end
$var reg 8 q \Register[1] [7:0] $end
$upscope $end
$upscope $end
$upscope $end
$scope module cpu_tb $end
$scope module mycpu $end
$scope module r1 $end
$var reg 8 r \Register[2] [7:0] $end
$upscope $end
$upscope $end
$upscope $end
$scope module cpu_tb $end
$scope module mycpu $end
$scope module r1 $end
$var reg 8 s \Register[3] [7:0] $end
$upscope $end
$upscope $end
$upscope $end
$scope module cpu_tb $end
$scope module mycpu $end
$scope module r1 $end
$var reg 8 t \Register[4] [7:0] $end
$upscope $end
$upscope $end
$upscope $end
$scope module cpu_tb $end
$scope module mycpu $end
$scope module r1 $end
$var reg 8 u \Register[5] [7:0] $end
$upscope $end
$upscope $end
$upscope $end
$scope module cpu_tb $end
$scope module mycpu $end
$scope module r1 $end
$var reg 8 v \Register[6] [7:0] $end
$upscope $end
$upscope $end
$upscope $end
$scope module cpu_tb $end
$scope module mycpu $end
$scope module r1 $end
$var reg 8 w \Register[7] [7:0] $end
$upscope $end
$upscope $end
$upscope $end
$enddefinitions $end
$comment Show the parameter values. $end
$dumpall
$end
#0
$dumpvars
bx w
bx v
bx u
bx t
bx s
bx r
bx q
bx p
bx o
bx n
bx00 m
bx l
bx k
bx j
bx i
bx h
bx g
bx f
bx e
bx d
bx c
bx b
bx a
bx `
bx _
bx ^
bx ]
bx \
bx [
bx Z
bx Y
bx X
bx W
bx00 V
bx U
bx T
bx S
bx R
bx Q
bx P
bx O
bx N
bx M
bx L
bx K
bx J
bx I
bx H
bx G
bx F
bx E
bx D
bx C
bx B
bx A
bx @
bx ?
x>
x=
x<
x;
bx :
x9
bx 8
bx 7
bx 6
bx 5
x4
bx 3
bx 2
bx 1
bx 0
bx /
bx .
bx -
bx ,
bx +
bx *
bx )
bx00 (
x'
bx &
b1000 %
0$
bx #
0"
bx !
$end
#2
1$
#4
1"
#5
b0 w
b0 v
b0 u
b0 t
b0 s
b0 r
b0 q
b0 p
b1000 i
b0 !
b0 5
b0 R
#6
b100 0
b100 S
b100 T
b100 ^
0$
#7
b0 )
b0 F
b0 c
b0 ,
b0 B
b0 H
b0 K
b0 M
b0 Q
b0 Y
b0 (
b0 V
b0 m
b101 7
b101 f
b0 6
b0 e
b0 :
b0 d
b101 W
b0 2
b0 k
b0 l
b0 j
b101 #
b101 &
#8
b100 +
b100 b
b100 *
b100 _
b100 a
b101 ,
b101 B
b101 H
b101 K
b101 M
b101 Q
b101 Y
04
b0 D
b0 G
b0 A
b0 P
0;
0=
b0 8
b0 ?
1<
0>
19
0"
#9
b0 -
b0 X
b0 \
bx1x1 @
bx1x1 J
b0x0x D
b0x0x G
b101 )
b101 F
b101 c
b101 A
b101 P
b100 3
b100 U
b100 ]
b100 `
b0 .
b0 Z
b0 h
b0 n
b0 /
b0 C
b0 I
b0 L
b0 N
b0 g
#10
b0 1
b0 [
b0 o
b101 @
b101 J
b0 D
b0 G
#11
0'
b101 E
b101 O
#12
1"
#13
b101 p
b100 !
b100 5
b100 R
#14
b1000 +
b1000 b
b1000 *
b1000 _
b1000 a
b1000 0
b1000 S
b1000 T
b1000 ^
#15
b1001 ,
b1001 B
b1001 H
b1001 K
b1001 M
b1001 Q
b1001 Y
b100 (
b100 V
b100 m
b1 7
b1 f
b1 :
b1 d
b1001 W
b1 2
b1 k
b1 l
b1 j
b101 /
b101 C
b101 I
b101 L
b101 N
b101 g
b10000000000001001 #
b10000000000001001 &
#16
b1101 @
b1101 J
b1001 )
b1001 F
b1001 c
b1001 A
b1001 P
b1 D
b1 G
0"
#17
b1100 3
b1100 U
b1100 ]
b1100 `
b1110 E
b1110 O
#20
1"
#21
b1001 q
b1000 !
b1000 5
b1000 R
#22
b1100 +
b1100 b
b1100 *
b1100 _
b1100 a
b1100 0
b1100 S
b1100 T
b1100 ^
#23
b1 ,
b1 B
b1 H
b1 K
b1 M
b1 Q
b1 Y
b1001 -
b1001 X
b1001 \
b10100 (
b10100 V
b10100 m
b101 :
b101 d
b1 W
b101 2
b101 k
b101 l
b101 j
b1001 .
b1001 Z
b1001 h
b1001 n
b1010000000000000001 #
b1010000000000000001 &
#24
b101 @
b101 J
b1 )
b1 F
b1 c
b1 A
b1 P
b11110111 1
b11110111 [
b11110111 o
0"
#25
b110 E
b110 O
b100000 3
b100000 U
b100000 ]
b100000 `
#28
1"
#29
b1 u
b1100 !
b1100 5
b1100 R
#30
b10000 +
b10000 b
b10000 *
b10000 _
b10000 a
b10000 0
b10000 S
b10000 T
b10000 ^
#31
b11100 (
b11100 V
b11100 m
b111 :
b111 d
b111 2
b111 k
b111 l
b111 j
b101000001110000000000000001 #
b101000001110000000000000001 &
#32
b1001 ,
b1001 B
b1001 H
b1001 K
b1001 M
b1001 Q
b1001 Y
b101 )
b101 F
b101 c
b11 8
b11 ?
0<
0"
#33
b1101 )
b1101 F
b1101 c
b1101 @
b1101 J
b1001 A
b1001 P
b101100 3
b101100 U
b101100 ]
b101100 `
#34
b1110 E
b1110 O
#36
1"
#37
b1101 w
b10000 !
b10000 5
b10000 R
#38
b10100 +
b10100 b
b10100 *
b10100 _
b10100 a
b10100 0
b10100 S
b10100 T
b10100 ^
#39
b1000 (
b1000 V
b1000 m
b10 :
b10 d
b10 2
b10 k
b10 l
b10 j
b1000000100000000000000001 #
b1000000100000000000000001 &
#40
b1001 )
b1001 F
b1001 c
b0 8
b0 ?
0"
#41
b11100 3
b11100 U
b11100 ]
b11100 `
#44
1"
#45
b1001 r
b10100 !
b10100 5
b10100 R
#46
b11000 +
b11000 b
b11000 *
b11000 _
b11000 a
b11000 0
b11000 S
b11000 T
b11000 ^
#47
b11000 (
b11000 V
b11000 m
b110 :
b110 d
b110 2
b110 k
b110 l
b110 j
b1000001100000000000000001 #
b1000001100000000000000001 &
#48
0"
#49
b110000 3
b110000 U
b110000 ]
b110000 `
#52
1"
#53
b1001 v
b11000 !
b11000 5
b11000 R
#54
b11100 +
b11100 b
b11100 *
b11100 _
b11100 a
b11100 0
b11100 S
b11100 T
b11100 ^
#55
b1100 (
b1100 V
b1100 m
b110 7
b110 f
b10 6
b10 e
b11 :
b11 d
b110 W
b11 2
b11 k
b11 l
b11 j
b111000000110000001000000110 #
b111000000110000001000000110 &
#56
b11110111 ,
b11110111 B
b11110111 H
b11110111 K
b11110111 M
b11110111 Q
b11110111 Y
b11110111 -
b11110111 X
b11110111 \
b1110 )
b1110 F
b1110 c
b1 8
b1 ?
1;
1>
09
0"
#57
b11110111 @
b11110111 J
b101 D
b101 G
b11110111 A
b11110111 P
b101000 3
b101000 U
b101000 ]
b101000 `
b1001 /
b1001 C
b1001 I
b1001 L
b1001 N
b1001 g
#58
b11111111 @
b11111111 J
b1 D
b1 G
#59
b101000 +
b101000 b
b101000 *
b101000 _
b101000 a
14
1'
b0 )
b0 F
b0 c
b0 E
b0 O
#60
1"
#61
b101000 !
b101000 5
b101000 R
#62
b101100 0
b101100 S
b101100 T
b101100 ^
#63
b1 7
b1 f
b0 6
b0 e
b1 W
b10000000110000000000000001 #
b10000000110000000000000001 &
#64
b1001 ,
b1001 B
b1001 H
b1001 K
b1001 M
b1001 Q
b1001 Y
b101100 +
b101100 b
b1001 -
b1001 X
b1001 \
b101100 *
b101100 _
b101100 a
04
0;
0>
19
b111000 3
b111000 U
b111000 ]
b111000 `
0"
#65
b1001 @
b1001 J
b1001 D
b1001 G
b1001 A
b1001 P
b101 /
b101 C
b101 I
b101 L
b101 N
b101 g
#66
b1101 @
b1101 J
b1 D
b1 G
#67
0'
b1110 )
b1110 F
b1110 c
b1110 E
b1110 O
#68
1"
#69
b1110 s
b101100 !
b101100 5
b101100 R
#70
b110000 +
b110000 b
b110000 *
b110000 _
b110000 a
b110000 0
b110000 S
b110000 T
b110000 ^
#71
b1000 (
b1000 V
b1000 m
b0 7
b0 f
b10 :
b10 d
b0 W
b10 2
b10 k
b10 l
b10 j
b110000000100000000000000000 #
b110000000100000000000000000 &
#72
b111000 +
b111000 b
b1001 )
b1001 F
b1001 c
1=
b0 8
b0 ?
09
0"
#73
b101 ,
b101 B
b101 H
b101 K
b101 M
b101 Q
b101 Y
b101 -
b101 X
b101 \
b101 .
b101 Z
b101 h
b101 n
#74
b101 @
b101 J
b101 D
b101 G
b101 )
b101 F
b101 c
b101 A
b101 P
b11111011 1
b11111011 [
b11111011 o
#75
b1010 E
b1010 O
#76
1"
#77
b111000 !
b111000 5
b111000 R
#78
b111100 *
b111100 _
b111100 a
b111100 0
b111100 S
b111100 T
b111100 ^
#79
b0 (
b0 V
b0 m
b10 7
b10 f
b0 :
b0 d
b10 W
b0 2
b0 k
b0 l
b0 j
b10 #
b10 &
#80
b111100 +
b111100 b
b10 ,
b10 B
b10 H
b10 K
b10 M
b10 Q
b10 Y
0=
1<
19
0"
#81
b1001 -
b1001 X
b1001 \
b111 @
b111 J
b0 D
b0 G
b10 )
b10 F
b10 c
b10 A
b10 P
b111100 3
b111100 U
b111100 ]
b111100 `
b1001 .
b1001 Z
b1001 h
b1001 n
#82
b11110111 1
b11110111 [
b11110111 o
b111 E
b111 O
#84
1"
#85
b10 p
b111100 !
b111100 5
b111100 R
#86
b1000000 +
b1000000 b
b1000000 *
b1000000 _
b1000000 a
b1000000 0
b1000000 S
b1000000 T
b1000000 ^
#87
b1 ,
b1 B
b1 H
b1 K
b1 M
b1 Q
b1 Y
b100 (
b100 V
b100 m
b1 7
b1 f
b1 :
b1 d
b1 W
b1 2
b1 k
b1 l
b1 j
b10 /
b10 C
b10 I
b10 L
b10 N
b10 g
b10000000000000001 #
b10000000000000001 &
#88
b1 )
b1 F
b1 c
b1 A
b1 P
b11 @
b11 J
0"
#89
b1000100 3
b1000100 U
b1000100 ]
b1000100 `
b11 E
b11 O
#92
1"
#93
b1 q
b1000000 !
b1000000 5
b1000000 R
#94
b1000100 +
b1000100 b
b1000100 *
b1000100 _
b1000100 a
b1000100 0
b1000100 S
b1000100 T
b1000100 ^
#95
b0 ,
b0 B
b0 H
b0 K
b0 M
b0 Q
b0 Y
b1 -
b1 X
b1 \
b10100 (
b10100 V
b10100 m
b0 7
b0 f
b1 6
b1 e
b101 :
b101 d
b0 W
b101 2
b101 k
b101 l
b101 j
b1 .
b1 Z
b1 h
b1 n
b100000001010000000100000000 #
b100000001010000000100000000 &
#96
b1 ,
b1 B
b1 H
b1 K
b1 M
b1 Q
b1 Y
b10 @
b10 J
b0 )
b0 F
b0 c
b0 A
b0 P
b11111111 1
b11111111 [
b11111111 o
b10 8
b10 ?
0<
0"
#97
b10 ,
b10 B
b10 H
b10 K
b10 M
b10 Q
b10 Y
b10 -
b10 X
b10 \
b11 @
b11 J
b1 A
b1 P
b1011000 3
b1011000 U
b1011000 ]
b1011000 `
b10 .
b10 Z
b10 h
b10 n
b1 /
b1 C
b1 I
b1 L
b1 N
b1 g
#98
b10 A
b10 P
b11111110 1
b11111110 [
b11111110 o
#100
1"
#101
b0 u
b1000100 !
b1000100 5
b1000100 R
#102
b1001000 +
b1001000 b
b1001000 *
b1001000 _
b1001000 a
b1001000 0
b1001000 S
b1001000 T
b1001000 ^
#103
b11100 (
b11100 V
b11100 m
b1 7
b1 f
b0 6
b0 e
b111 :
b111 d
b1 W
b111 2
b111 k
b111 l
b111 j
b101000001110000000000000001 #
b101000001110000000000000001 &
#104
b11 )
b11 F
b11 c
b11 8
b11 ?
0"
#105
b1 ,
b1 B
b1 H
b1 K
b1 M
b1 Q
b1 Y
b1 -
b1 X
b1 \
b1100100 3
b1100100 U
b1100100 ]
b1100100 `
b1 .
b1 Z
b1 h
b1 n
b10 /
b10 C
b10 I
b10 L
b10 N
b10 g
#106
b1 A
b1 P
b11111111 1
b11111111 [
b11111111 o
#108
1"
#109
b11 w
b1001000 !
b1001000 5
b1001000 R
#110
b1001100 +
b1001100 b
b1001100 *
b1001100 _
b1001100 a
b1001100 0
b1001100 S
b1001100 T
b1001100 ^
#111
b10000 (
b10000 V
b10000 m
b101 7
b101 f
b11 6
b11 e
b100 :
b100 d
b101 W
b100 2
b100 k
b100 l
b100 j
b11000001000000001100000101 #
b11000001000000001100000101 &
#112
b11111111 ,
b11111111 B
b11111111 H
b11111111 K
b11111111 M
b11111111 Q
b11111111 Y
b11111111 -
b11111111 X
b11111111 \
b1 8
b1 ?
1>
0"
#113
b11111111 @
b11111111 J
b10 D
b10 G
b11111111 A
b11111111 P
b1011100 3
b1011100 U
b1011100 ]
b1011100 `
b0 .
b0 Z
b0 h
b0 n
b1110 /
b1110 C
b1110 I
b1110 L
b1110 N
b1110 g
