group27_lab6_part1/reg_file.v
/* Lab 5 : Part 4 Flow Control Instructions - reg file
   Group 27
*/

///////////////////////////    register file      ///////////////////////////////////
module register_file(DATAINIn, Output_1, Output_2, DATAINInAddress, OutputAddress_1, OutputAddress_2, WRITE, CLK, RESET);

    reg [7:0] Register[0:7]; //8, 8 bit registers inside

    //declaration of inputs and ouputs
    input [7:0] DATAINIn;
    input [2:0] OutputAddress_1, OutputAddress_2, DATAINInAddress;
    input CLK, RESET, WRITE;
    output [7:0] Output_1, Output_2;

    integer i;

    //read asynchronously and load values into Output_1 and Output_2 
    assign #2 Output_1 = Register[OutputAddress_1];
    assign #2 Output_2 = Register[OutputAddress_2];

    //always block only teriggerd in the positive edge of clock
    always@(posedge CLK)
    begin
        if(WRITE & !RESET) begin// if write port is set to high and reset is low then IN port is write into register named as DATAINInAddress
           #1 Register[DATAINInAddress] <= DATAINIn;
        end
        if(RESET) begin // if reset is high, all values in registers are written as 0
            #1
            for(i = 0; i < 8; i += 1) begin // make for loop for access each element in an array
                Register[i] = 8'd0;
            end
        end

    end

endmodule
//////////////////////////////////////////////////////////////////////////////////////////////////

group27_lab5_part5/alu.v
/* Lab 5 : Part 4 Flow Control Instructions - ALU
   Group 27
*/


//////////////////////////       ALU          /////////////////////////////////////////////////////////////////
module alu(DATAIN1, DATAIN2, RESULT, SELECT, ZERO, SHIFT_SEL);

    //port declaration
    // inputs
    input [7 : 0] DATAIN1, DATAIN2;
    input [2 : 0] SELECT;
    input [1:0] SHIFT_SEL;
    // outputs
    output reg [7 : 0] RESULT;  
    wire [7 : 0] FWD_OUT, ADD_OUT, AND_OUT, OR_OUT, SHIFT_OUT, MULTI_OUT; //get outputs from the function modules
    output reg ZERO;

    //instantiate function modules
    FORWARD fwd(DATAIN2, FWD_OUT);
    ADD add(DATAIN1, DATAIN2, ADD_OUT);
    AND And(DATAIN1, DATAIN2, AND_OUT);
    OR Or(DATAIN1, DATAIN2, OR_OUT);
    SHIFT shift(DATAIN1, DATAIN2, SHIFT_OUT, SHIFT_SEL);
    MULTI mult(DATAIN1, DATAIN2, MULTI_OUT);

     always@(ADD_OUT) begin
       if(ADD_OUT == 0) ZERO = 1; //set ZERO signal to high if answer of subrtraction is ZERO
      else ZERO = 0; // otherwise set it to low
     end

     //selecting the relevant output result according to the SELECT input
    always @(DATAIN1,DATAIN2,SELECT)
    begin
        case (SELECT)
            3'b000 : assign RESULT = FWD_OUT;   //SELECT 000 -> FORWARD
            3'b001 : assign RESULT = ADD_OUT;  //SELECT 001 -> ADD
            3'b010 : assign RESULT = AND_OUT;  //SELECT 010 -> AND
            3'b011 : assign RESULT = OR_OUT;   //SELECT 011 -> OR
            3'b100 : assign RESULT = SHIFT_OUT; // SELECT 100 -> SHIFTED RESULT
            3'b101 : assign RESULT = MULTI_OUT; // SELECT 101 -> DATA1 x DATA2
            default: assign RESULT = 8'd0;        
        endcase
        
    end

endmodule

// FORWARD module - for loadi, mov instructions
module FORWARD(DATAIN2, FWD_OUT);

    // port declaration
    input [7 : 0] DATAIN2;
    output [7 : 0] FWD_OUT;

    assign #1 FWD_OUT = DATAIN2; // wait for 1 time unit and assign value of DATAIN2 to FWD_OUT
endmodule


// ADD module - for add, sub instructions
module ADD(DATAIN1, DATAIN2, ADD_OUT);

    // port declaration
    input [7 : 0] DATAIN1;
    input [7 : 0] DATAIN2;
    output [7 : 0] ADD_OUT;

    assign #2 ADD_OUT = DATAIN1 + DATAIN2; // wait for 2 time unit and assign sum of DATAIN1 and DATAIN2 to ADD_OUT

endmodule

// AND module - for and instruction
module AND(DATAIN1, DATAIN2, AND_OUT);

    // port declaration
    input [7 : 0] DATAIN1;
    input [7 : 0] DATAIN2;
    output [7 : 0] AND_OUT;

    assign #1 AND_OUT = DATAIN1 & DATAIN2; // wait for 1 time unit and assign AND of DATAIN1 and DATAIN2 to AND_OUT

endmodule

// OR module - for or instruction
module OR(DATAIN1, DATAIN2, OR_OUT);

    // port declaration
    input [7 : 0] DATAIN1;
    input [7 : 0] DATAIN2;
    output [7 : 0] OR_OUT;

    assign #1 OR_OUT = DATAIN1 | DATAIN2; // wait for 1 time unit and assign OR of DATAIN1 and DATAIN2 to OR_OUT

endmodule

//module for shifting
module SHIFT(DATA, SHIFT_AMOUNT, OUT, Shift_SEL);
    input [7:0]DATA, SHIFT_AMOUNT;
    output reg[7:0] OUT;
    input [1:0] Shift_SEL;

    always@(*) begin
        #1
        //logical right shift
        case(Shift_SEL)
        2'b00 : begin 
            case(SHIFT_AMOUNT)
            8'd0 : OUT = DATA;   
            8'd1 : OUT = {{1{1'b0}}, DATA[7:1]}; //append 0 to front and select necessary bits according to shift amount
            8'd2 : OUT = {{2{1'b0}}, DATA[7:2]};
            8'd3 : OUT = {{3{1'b0}}, DATA[7:3]};
            8'd4 : OUT = {{4{1'b0}}, DATA[7:4]};
            8'd5 : OUT = {{5{1'b0}}, DATA[7:5]};
            8'd6 : OUT = {{6{1'b0}}, DATA[7:6]};
            8'd7 : OUT = {{7{1'b0}}, DATA[7:7]};
            default : OUT = {7{1'b0}};  
            endcase
            end

        //logical left shift
        2'b01 : begin 
            
            case(SHIFT_AMOUNT)
            8'd0 : OUT = DATA;
            8'd1 : OUT = {DATA[6:0], {1{1'b0}}}; //append 0 to back and select necessary bits according to shift amount
            8'd2 : OUT = {DATA[5:0], {2{1'b0}}};
            8'd3 : OUT = {DATA[4:0], {3{1'b0}}};
            8'd4 : OUT = {DATA[3:0], {4{1'b0}}};
            8'd5 : OUT = {DATA[2:0], {5{1'b0}}};
            8'd6 : OUT = {DATA[1:0], {6{1'b0}}};
            8'd7 : OUT = {DATA[0:0], {7{1'b0}}};
            default : OUT = {7{1'b0}};  
            endcase
            end

        //arithmetic right shift
        2'b10 : begin 
            case(SHIFT_AMOUNT)
            8'd0 : OUT = DATA;
            8'd1 : OUT = {{1{DATA[7]}}, DATA[7:1]}; //append msb to front and select necessary bits according to shift amount
            8'd2 : OUT = {{2{DATA[7]}}, DATA[7:2]};
            8'd3 : OUT = {{3{DATA[7]}}, DATA[7:3]};
            8'd4 : OUT = {{4{DATA[7]}}, DATA[7:4]};
            8'd5 : OUT = {{5{DATA[7]}}, DATA[7:5]};
            8'd6 : OUT = {{6{DATA[7]}}, DATA[7:6]};
            8'd7 : OUT = {{7{DATA[7]}}, DATA[7:7]};
            default : OUT = {7{DATA[7]}}; 
            endcase
            end

        //rotate shift
        2'b11 : begin 
            case(SHIFT_AMOUNT%8)
            8'd0 : OUT = DATA;
            8'd1 : OUT = {DATA[0], DATA[7:1]}; //rotate necessary bits according to shift amount
            8'd2 : OUT = {DATA[1:0], DATA[7:2]};
            8'd3 : OUT = {DATA[2:0], DATA[7:3]};
            8'd4 : OUT = {DATA[3:0], DATA[7:4]};
            8'd5 : OUT = {DATA[4:0], DATA[7:5]};
            8'd6 : OUT = {DATA[5:0], DATA[7:6]};
            8'd7 : OUT = {DATA[6:0], DATA[7:7]};
            endcase
            end
        endcase
    end
endmodule

//module for multiply
module MULTI(DATA1, DATA2, OUT);
    input [7:0] DATA1, DATA2;
    output [7:0] OUT;
    wire [7:0] p0, p1, p2, p3, p4, p5, p6, p7;
    reg [7:0] pr;
    
  always @* begin
    pr = 8'd0;  //product is initially zero
                // check for each bit in the multiplier while right shifting. if the bit is 1 add the multiplicand to the 
                // the product. then left shift the multiplicand 
    
    if (DATA2[0] == 1) pr = pr + DATA1;
    if (DATA2[1] == 1) pr = pr + {DATA1[6:0], 1'b0};
    if (DATA2[2] == 1) pr = pr + {DATA1[5:0], 2'b00};
    if (DATA2[3] == 1) pr = pr + {DATA1[4:0], 3'b000};
    if (DATA2[4] == 1) pr = pr + {DATA1[4:0], 4'b0000};
    if (DATA2[5] == 1) pr = pr + {DATA1[2:0], 5'b00000};
    if (DATA2[6] == 1) pr = pr + {DATA1[1:0], 6'b000000};
    if (DATA2[7] == 1) pr = pr + {DATA1[0], 7'b0000000};
  end
    

       assign #2 OUT = pr;  //output of the product

endmodule
///////////////////////////////////////////////////////////////////////////////////////////////////

group27_lab5_part5/lab5part5.v
/* Lab 5 : Part 4 Flow Control Instructions
   Group 27
*/

`include "alu.v"
`include "reg_file.v"

/////////////////////////////////////////////////// CPU_tb/////////////////////////////////////////////////////////////////

module cpu_tb;

    reg CLK, RESET;
    wire [31:0] PC;
    reg [31:0] INSTRUCTION;
    integer i;
    
    /* 
    ------------------------
     SIMPLE INSTRUCTION MEM
    ------------------------
    */
    
    // TODO: Initialize an array of registers (8x1024) named 'instr_mem' to be used as instruction memory
    reg [7:0] instr_mem[0:1023];
    
    // TODO: Create combinational logic to support CPU instruction fetching, given the Program Counter(PC) value 
    //       (make sure you include the delay for instruction fetching here)
    always @(PC) begin
        #2
        INSTRUCTION = {instr_mem[PC+3], instr_mem[PC+2], instr_mem[PC+1], instr_mem[PC]};
    end
    
    initial
    begin
        // Initialize instruction memory with the set of instructions you need execute on CPU
        
        // METHOD 1: manually loading instructions to instr_mem
        //{instr_mem[10'd3], instr_mem[10'd2], instr_mem[10'd1], instr_mem[10'd0]} = 32'b00000000000001000000000000000101;
        //{instr_mem[10'd7], instr_mem[10'd6], instr_mem[10'd5], instr_mem[10'd4]} = 32'b00000000000000100000000000001001;
        //{instr_mem[10'd11], instr_mem[10'd10], instr_mem[10'd9], instr_mem[10'd8]} = 32'b00000010000001100000010000000010;
        
        // METHOD 2: loading instr_mem content from instr_mem.mem file
       $readmemb("instr_mem.mem", instr_mem);
    end
    
    /* 
    -----
     CPU
    -----
    */
    cpu mycpu(PC, INSTRUCTION, CLK, RESET);

    initial
    begin
    
        // generate files needed to plot the waveform using GTKWave
        $dumpfile("cpu_wavedata.vcd");
		$dumpvars(0, cpu_tb);

        for(i=0;i<8;i=i+1)
        begin
            $dumpvars(1,cpu_tb.mycpu.r1.Register[i]);
        end 
        
        CLK = 1'b0;
        RESET = 1'b0;
        
        // TODO: Reset the CPU (by giving a pulse to RESET signal) to start the program execution
        #2
        RESET = 1'b1;

        #4
        RESET= 1'b0;
        
        // finish simulation after some time
        #500
        $finish;
        
    end
    
    // clock signal generation
    always
        #4 CLK = ~CLK;
        
endmodule

//////////////////////////////////////////////////   CPU     ////////////////////////////////////////////////////////////////
module cpu(PC, INSTRUCTION, CLK, RESET);
    output reg [31:0] PC;
    input [31:0] INSTRUCTION;
    input CLK, RESET;

    wire [7:0] OUT1, OUT2, OUT3, OUT4, NEGATIVE,RESULT;
    reg [2:0] WRITE_ADRS,READ_ADRS1, READ_ADRS2, SEL;
    reg [1:0] SHIFT_SEL;
    reg [7:0] BRANCH;
    reg WRITE , isNEGATIVE, isIMMEDIATE, isBRANCH, isJUMP, isNEqBRANCH;

    wire [31:0] NEXT_INS,EXTENDED, SHIFTED, BRANCHto, PCbranch, PCNEXT;
    wire ZERO,AND_OUT,AND_OUT2, OR_OUT;


    //instantiate all sub modules
    alu a1(OUT1, OUT4, RESULT, SEL, ZERO, SHIFT_SEL);
    register_file r1(RESULT, OUT1, OUT2, WRITE_ADRS,READ_ADRS1, READ_ADRS2, WRITE, CLK, RESET);
    PC_adder add(PC, NEXT_INS); 
    twosCompliment t1(OUT2, NEGATIVE); // get 2's compliment
    MUX isNeg(NEGATIVE, OUT2, OUT3, isNEGATIVE); //select negative value for sub instruction and positive value for add instruction
    MUX isIMM(INSTRUCTION[7:0], OUT3, OUT4, isIMMEDIATE); //select immediate value or register value 

    AND2 and_gate(ZERO, isBRANCH, AND_OUT); //get the AND value of Zero and isBranch to do beq instruction
    PC_MUX m1(BRANCHto, NEXT_INS, PCbranch, OR_OUT); // select next pc value according to OR output
    Sign_extend s1(INSTRUCTION[23:16], EXTENDED); // sign extend given value to 32 bit before find the offset
    shift shift_2(EXTENDED, SHIFTED); // multiply the sign extended value by 4.(shift 2)
    Branch_ADD brAdd(NEXT_INS, SHIFTED, BRANCHto); // calculate the new PC value using shifted value
    PC_MUX m2(BRANCHto, PCbranch, PCNEXT, isJUMP); // select jump or branch to decide next PC value

    AND2 and_gate2(~ZERO, isNEqBRANCH, AND_OUT2);
    OR_GT or1(AND_OUT,AND_OUT2,OR_OUT);

    always @(posedge CLK) begin
        if (RESET == 1'b1) 
		begin
			#1
			PC = 0;		 //When  the reset is 1 PC should be 0
		end
        else #1 PC = PCNEXT;         //PC update (delay 1 unit)
            
    end

    always @(INSTRUCTION) begin

        //assign instuction to reg_file inputs
        WRITE_ADRS = INSTRUCTION[18:16];
        READ_ADRS1 = INSTRUCTION[10:8];
        READ_ADRS2 = INSTRUCTION[2:0];

        //Control Unit
        //check opcode and decode
        #1
        case(INSTRUCTION[31:24]) 
            8'd0 : //loadi instruction
                begin
                    WRITE = 1;          //enable write 
                    isNEGATIVE = 1'b0;  //no need for subtraction
                    isIMMEDIATE = 1'b1; //loadi instruction contain immediate value
                    SEL = 3'b000;       //select alu FORWARD operation
                    isJUMP = 1'b0;      //no instruction jumps
                    isBRANCH = 1'b0;    //no branchings
                    isNEqBRANCH = 1'b0; 

                end
            8'd1 : //mov instruction
                begin
                    WRITE = 1;          //enable write
                    isNEGATIVE = 1'b0;  //no need for subtraction
                    isIMMEDIATE = 1'b0; //no immediate value
                    SEL = 3'b000;       //select alu FORWARD operation
                    isJUMP = 1'b0;
                    isBRANCH = 1'b0;
                    isNEqBRANCH = 1'b0;

                end
            8'd2 : //add instruction 
                begin
                    WRITE = 1;          //enable write
                    isNEGATIVE = 1'b0;  //no need for subtraction
                    isIMMEDIATE = 1'b0; //no immediate value
                    SEL = 3'b001;       //select alu ADD operation
                    isJUMP = 1'b0;
                    isBRANCH = 1'b0;
                    isNEqBRANCH = 1'b0;
                    
                end
            8'd3 : //sub instruction
                begin
                    WRITE = 1;          //enable write
                    isNEGATIVE = 1'b1;  //need to substract value so isNegative is high
                    isIMMEDIATE = 1'b0; //no immediate value
                    SEL = 3'b001;       //select alu ADD operation
                    isJUMP = 1'b0;
                    isBRANCH = 1'b0;
                    isNEqBRANCH = 1'b0;
                    
                end
            8'd4 : //and instruction 
                begin
                    WRITE = 1;           //enable write
                    isNEGATIVE = 1'b0;   //no need for subtraction
                    isIMMEDIATE = 1'b0;  //no immediate value
                    SEL = 3'b010;        //select alu AND operation
                    isJUMP = 1'b0;
                    isBRANCH = 1'b0;
                    isNEqBRANCH = 1'b0;
                    
                end
            8'd5 : //or instruction
                begin
                    WRITE = 1;           //enable write
                    isNEGATIVE = 1'b0;   //no need for subtraction
                    isIMMEDIATE = 1'b0;  //no immediate value
                    SEL = 3'b011;        //select alu OR operation 
                    isJUMP = 1'b0;
                    isBRANCH = 1'b0;
                    isNEqBRANCH = 1'b0;
                    
                end
            8'd6 : //jump instruction
                begin
                    WRITE = 0;          // not writing to the register
                    isNEGATIVE = 1'b0;  //no need for subtraction
                    isIMMEDIATE = 1'b0; // no immidiate value
                    SEL = 3'b000;       //no need alu operation
                    isJUMP = 1'b1;      // jump signal is high
                    isBRANCH = 1'b0;    // no branchings
                    isNEqBRANCH = 1'b0;
                    
                end
            8'd7 : //branch instruction
                begin
                    WRITE = 0;          // not writing to the register 
                    isNEGATIVE = 1'b1;  // get negative value for subtraction
                    isIMMEDIATE = 1'b0; // dont need immidiate values
                    isJUMP = 1'b0;      // jump is low
                    isBRANCH = 1'b1;    // branch signal is high
                    SEL = 3'b001;       //select alu ADD operation
                    isNEqBRANCH = 1'b0;
                    
                end

            8'd12 : //logical shift left
                begin
                    WRITE = 1;          // write final result to the register 
                    isNEGATIVE = 1'b0;  // no need negative value
                    isIMMEDIATE = 1'b1; // need immidiate values
                    isJUMP = 1'b0;      // jump signal  is low
                    isBRANCH = 1'b0;    // branch signal is low
                    SEL = 3'b100;       //select alu shift operation
                    SHIFT_SEL = 2'b01;  //select sll operation
                    isNEqBRANCH = 1'b0; 
                    
                end
            8'd13 : //logical shift right
                begin
                    WRITE = 1;          // write final result to the register 
                    isNEGATIVE = 1'b0;  // no need negative value
                    isIMMEDIATE = 1'b1; // need immidiate values
                    isJUMP = 1'b0;      // jump signal  is low
                    isBRANCH = 1'b0;    // branch signal is low
                    SEL = 3'b100;       //select alu shift operation
                    SHIFT_SEL = 2'b00;  //select srl operation
                    isNEqBRANCH = 1'b0; 
                    
                end
           8'd14 : //arithmatic shift right
                begin
                    WRITE = 1;          // write final result to the register 
                    isNEGATIVE = 1'b0;  // no need negative value
                    isIMMEDIATE = 1'b1; // need immidiate values
                    isJUMP = 1'b0;      // jump signal  is low
                    isBRANCH = 1'b0;    // branch signal is low
                    SEL = 3'b100;       //select alu shift operation
                    SHIFT_SEL = 2'b10;  //select sra operation
                    isNEqBRANCH = 1'b0; 
                    
                end
            8'd15 : //rotate right
                begin
                    WRITE = 1;          // write final result to the register 
                    isNEGATIVE = 1'b0;  // no need negative value
                    isIMMEDIATE = 1'b1; // need immidiate values
                    isJUMP = 1'b0;      // jump signal  is low
                    isBRANCH = 1'b0;    // branch signal is low
                    SEL = 3'b100;       //select alu shift operation
                    SHIFT_SEL = 2'b11;  //select ror operation
                    isNEqBRANCH = 1'b0; 
                    
                end
            8'd16 : //branch not equal
                begin
                    WRITE = 0;          // not writing results to the register 
                    isNEGATIVE = 1'b1;  // make second operand to negative
                    isIMMEDIATE = 1'b0; // don't need immidiate values
                    isJUMP = 1'b0;      // jump signal  is low
                    isBRANCH = 1'b0;    // branch signal is low
                    SEL = 3'b001;       //select alu sub operation
                    isNEqBRANCH = 1'b1;  // not equal branch signal is high
                     
                end
           8'd17 : //multiply
                begin
                    WRITE = 1;          // write final result to the register 
                    isNEGATIVE = 1'b0;  // no need negative value
                    isIMMEDIATE = 1'b0; // don't need immidiate values
                    isJUMP = 1'b0;      // jump signal  is low
                    isBRANCH = 1'b0;    // branch signal is low
                    SEL = 3'b101;       //select alu multi operation
                    isNEqBRANCH = 1'b0;  
                     
                end
            
            
            
        endcase
    
    end

    

endmodule

/////////////////////////////////////////

 //module for 2's compliment
module twosCompliment(DATAIN, OUT);
   //declare input and output
   input [7:0] DATAIN;
   output [7:0] OUT;
   assign #1 OUT = ~DATAIN + 1;  //get 2's compliment by negating and adding 1
endmodule

//module for the selector MUX
module MUX(IN1, IN2, OUT, SELECT);
    input [7:0] IN1, IN2;
    input SELECT;
    output reg [7:0] OUT;

    always@(*) begin
        case(SELECT)
            1'b1: OUT <= IN1;
            1'b0: OUT <= IN2;
            default: OUT <= 8'd0;
        endcase
    end
endmodule

// dedicated adder for PC 
module PC_adder(IN, NEXT_INS);
    input [31:0] IN; // input address (current instruction)
    output [31:0] NEXT_INS; // output address (NEXT_INS instruction)

    assign #1 NEXT_INS = IN + 32'd4; // increment the PC value by 4 (delay 1 time unit)
  
endmodule

// AND gate module
module AND2(INPUT1,INPUT2,OUTPUT);
    input INPUT1,INPUT2;
    output OUTPUT;

    and(OUTPUT,INPUT1,INPUT2); 
endmodule

//OR gate module
module OR_GT(IN1, IN2, OUT);
    input IN1, IN2;
    output OUT;

    or(OUT, IN1, IN2);

endmodule

///////////////////////////////////////
//module for Add offset value to PC value for branching
module Branch_ADD(pcNext, offset, out);
    input [31:0] pcNext, offset;
    output [31:0] out;

    assign #2 out = pcNext + offset;

endmodule

//module for sign extend
module Sign_extend(IN, OUT);
    input [7:0] IN; //8 bit input
    output [31:0] OUT; //32 bit output

    assign OUT[7:0] = IN[7:0];
    assign OUT[31:8] = {24{IN[7]}};
    initial begin
    end
endmodule

//module for shift 2 times
module shift(IN, OUT);
    input signed[31:0] IN;
    output signed[31:0] OUT;

    assign OUT = IN << 2; // multiply by 4

endmodule

//mux module for select right pc value
module PC_MUX(IN1, IN2, OUT, SELECT);
    input [31:0] IN1, IN2;
    input SELECT;
    output reg [31:0] OUT;

    always@(*) begin
        case(SELECT)
            1'b1: OUT <= IN1;
            1'b0: OUT <= IN2;
        endcase
    end
endmodule

group27_lab5_part5/cpu_wavedata.vcd
$date
	Wed Jun 07 11:04:27 2023
$end
$version
	Icarus Verilog
$end
$timescale
	1s
$end
$scope module cpu_tb $end
$var wire 32 ! PC [31:0] $end
$var reg 1 " CLK $end
$var reg 32 # INSTRUCTION [31:0] $end
$var reg 1 $ RESET $end
$var integer 32 % i [31:0] $end
$scope module mycpu $end
$var wire 1 " CLK $end
$var wire 32 & INSTRUCTION [31:0] $end
$var wire 1 $ RESET $end
$var wire 1 ' ZERO $end
$var wire 32 ( SHIFTED [31:0] $end
$var wire 8 ) RESULT [7:0] $end
$var wire 32 * PCbranch [31:0] $end
$var wire 32 + PCNEXT [31:0] $end
$var wire 8 , OUT4 [7:0] $end
$var wire 8 - OUT3 [7:0] $end
$var wire 8 . OUT2 [7:0] $end
$var wire 8 / OUT1 [7:0] $end
$var wire 1 0 OR_OUT $end
$var wire 32 1 NEXT_INS [31:0] $end
$var wire 8 2 NEGATIVE [7:0] $end
$var wire 32 3 EXTENDED [31:0] $end
$var wire 32 4 BRANCHto [31:0] $end
$var wire 1 5 AND_OUT2 $end
$var wire 1 6 AND_OUT $end
$var reg 32 7 PC [31:0] $end
$var reg 3 8 READ_ADRS1 [2:0] $end
$var reg 3 9 READ_ADRS2 [2:0] $end
$var reg 3 : SEL [2:0] $end
$var reg 2 ; SHIFT_SEL [1:0] $end
$var reg 1 < WRITE $end
$var reg 3 = WRITE_ADRS [2:0] $end
$var reg 1 > isBRANCH $end
$var reg 1 ? isIMMEDIATE $end
$var reg 1 @ isJUMP $end
$var reg 1 A isNEGATIVE $end
$var reg 1 B isNEqBRANCH $end
$scope module a1 $end
$var wire 3 C SELECT [2:0] $end
$var wire 2 D SHIFT_SEL [1:0] $end
$var wire 8 E SHIFT_OUT [7:0] $end
$var wire 8 F OR_OUT [7:0] $end
$var wire 8 G MULTI_OUT [7:0] $end
$var wire 8 H FWD_OUT [7:0] $end
$var wire 8 I DATAIN2 [7:0] $end
$var wire 8 J DATAIN1 [7:0] $end
$var wire 8 K AND_OUT [7:0] $end
$var wire 8 L ADD_OUT [7:0] $end
$var reg 8 M RESULT [7:0] $end
$var reg 1 ' ZERO $end
$scope module And $end
$var wire 8 N AND_OUT [7:0] $end
$var wire 8 O DATAIN2 [7:0] $end
$var wire 8 P DATAIN1 [7:0] $end
$upscope $end
$scope module Or $end
$var wire 8 Q OR_OUT [7:0] $end
$var wire 8 R DATAIN2 [7:0] $end
$var wire 8 S DATAIN1 [7:0] $end
$upscope $end
$scope module add $end
$var wire 8 T DATAIN2 [7:0] $end
$var wire 8 U DATAIN1 [7:0] $end
$var wire 8 V ADD_OUT [7:0] $end
$upscope $end
$scope module fwd $end
$var wire 8 W FWD_OUT [7:0] $end
$var wire 8 X DATAIN2 [7:0] $end
$upscope $end
$scope module mult $end
$var wire 8 Y OUT [7:0] $end
$var wire 8 Z DATA2 [7:0] $end
$var wire 8 [ DATA1 [7:0] $end
$var reg 8 \ pr [7:0] $end
$upscope $end
$scope module shift $end
$var wire 2 ] Shift_SEL [1:0] $end
$var wire 8 ^ SHIFT_AMOUNT [7:0] $end
$var wire 8 _ DATA [7:0] $end
$var reg 8 ` OUT [7:0] $end
$upscope $end
$upscope $end
$scope module add $end
$var wire 32 a IN [31:0] $end
$var wire 32 b NEXT_INS [31:0] $end
$upscope $end
$scope module and_gate $end
$var wire 1 ' INPUT1 $end
$var wire 1 > INPUT2 $end
$var wire 1 6 OUTPUT $end
$upscope $end
$scope module and_gate2 $end
$var wire 1 c INPUT1 $end
$var wire 1 B INPUT2 $end
$var wire 1 5 OUTPUT $end
$upscope $end
$scope module brAdd $end
$var wire 32 d pcNext [31:0] $end
$var wire 32 e out [31:0] $end
$var wire 32 f offset [31:0] $end
$upscope $end
$scope module isIMM $end
$var wire 8 g IN1 [7:0] $end
$var wire 1 ? SELECT $end
$var wire 8 h IN2 [7:0] $end
$var reg 8 i OUT [7:0] $end
$upscope $end
$scope module isNeg $end
$var wire 1 A SELECT $end
$var wire 8 j IN2 [7:0] $end
$var wire 8 k IN1 [7:0] $end
$var reg 8 l OUT [7:0] $end
$upscope $end
$scope module m1 $end
$var wire 32 m IN1 [31:0] $end
$var wire 32 n IN2 [31:0] $end
$var wire 1 0 SELECT $end
$var reg 32 o OUT [31:0] $end
$upscope $end
$scope module m2 $end
$var wire 32 p IN1 [31:0] $end
$var wire 32 q IN2 [31:0] $end
$var wire 1 @ SELECT $end
$var reg 32 r OUT [31:0] $end
$upscope $end
$scope module or1 $end
$var wire 1 6 IN1 $end
$var wire 1 5 IN2 $end
$var wire 1 0 OUT $end
$upscope $end
$scope module r1 $end
$var wire 1 " CLK $end
$var wire 8 s DATAINIn [7:0] $end
$var wire 3 t DATAINInAddress [2:0] $end
$var wire 3 u OutputAddress_1 [2:0] $end
$var wire 3 v OutputAddress_2 [2:0] $end
$var wire 8 w Output_1 [7:0] $end
$var wire 8 x Output_2 [7:0] $end
$var wire 1 $ RESET $end
$var wire 1 < WRITE $end
$var integer 32 y i [31:0] $end
$upscope $end
$scope module s1 $end
$var wire 8 z IN [7:0] $end
$var wire 32 { OUT [31:0] $end
$upscope $end
$scope module shift_2 $end
$var wire 32 | IN [31:0] $end
$var wire 32 } OUT [31:0] $end
$upscope $end
$scope module t1 $end
$var wire 8 ~ DATAIN [7:0] $end
$var wire 8 !" OUT [7:0] $end
$upscope $end
$upscope $end
$upscope $end
$scope module cpu_tb $end
$scope module mycpu $end
$scope module r1 $end
$var reg 8 "" \Register[0] [7:0] $end
$upscope $end
$upscope $end
$upscope $end
$scope module cpu_tb $end
$scope module mycpu $end
$scope module r1 $end
$var reg 8 #" \Register[1] [7:0] $end
$upscope $end
$upscope $end
$upscope $end
$scope module cpu_tb $end
$scope module mycpu $end
$scope module r1 $end
$var reg 8 $" \Register[2] [7:0] $end
$upscope $end
$upscope $end
$upscope $end
$scope module cpu_tb $end
$scope module mycpu $end
$scope module r1 $end
$var reg 8 %" \Register[3] [7:0] $end
$upscope $end
$upscope $end
$upscope $end
$scope module cpu_tb $end
$scope module mycpu $end
$scope module r1 $end
$var reg 8 &" \Register[4] [7:0] $end
$upscope $end
$upscope $end
$upscope $end
$scope module cpu_tb $end
$scope module mycpu $end
$scope module r1 $end
$var reg 8 '" \Register[5] [7:0] $end
$upscope $end
$upscope $end
$upscope $end
$scope module cpu_tb $end
$scope module mycpu $end
$scope module r1 $end
$var reg 8 (" \Register[6] [7:0] $end
$upscope $end
$upscope $end
$upscope $end
$scope module cpu_tb $end
$scope module mycpu $end
$scope module r1 $end
$var reg 8 )" \Register[7] [7:0] $end
$upscope $end
$upscope $end
$upscope $end
$enddefinitions $end
$comment Show the parameter values. $end
$dumpall
$end
#0
$dumpvars
bx )"
bx ("
bx '"
bx &"
bx %"
bx $"
bx #"
bx ""
bx !"
bx ~
bx00 }
bx |
bx {
bx z
bx y
bx x
bx w
bx v
bx u
bx t
bx s
bx r
bx q
bx p
bx o
bx n
bx m
bx l
bx k
bx j
bx i
bx h
bx g
bx00 f
bx e
bx d
xc
bx b
bx a
bx `
bx _
bx ^
bx ]
bx \
bx [
bx Z
bx Y
bx X
bx W
bx V
bx U
bx T
bx S
bx R
bx Q
bx P
bx O
bx N
bx M
bx L
bx K
bx J
bx I
bx H
bx G
bx F
bx E
bx D
bx C
xB
xA
x@
x?
x>
bx =
x<
bx ;
bx :
bx 9
bx 8
bx 7
x6
x5
bx 4
bx 3
bx 2
bx 1
x0
bx /
bx .
bx -
bx ,
bx +
bx *
bx )
bx00 (
x'
bx &
b1000 %
0$
bx #
0"
bx !
$end
#2
1$
#4
1"
#5
b0 )"
b0 ("
b0 '"
b0 &"
b0 %"
b0 $"
b0 #"
b0 ""
b1000 y
b0 !
b0 7
b0 a
#6
b100 1
b100 b
b100 d
b100 n
0$
#7
b0 )
b0 M
b0 s
b0 \
b0 ,
b0 I
b0 O
b0 R
b0 T
b0 X
b0 Z
b0 ^
b0 i
b0 (
b0 f
b0 }
b101 9
b101 v
b0 8
b0 u
b0 =
b0 t
b101 g
b0 3
b0 {
b0 |
b0 z
b101 #
b101 &
#8
b100 +
b100 r
bx \
b100 *
b100 o
b100 q
b101 ,
b101 I
b101 O
b101 R
b101 T
b101 X
b101 Z
b101 ^
b101 i
00
05
06
b0 K
b0 N
b0 H
b0 W
0B
0>
0@
b0 :
b0 C
1?
0A
1<
0"
#9
b0 -
b0 h
b0 l
b0 \
bx1x1 F
bx1x1 Q
b0x0x K
b0x0x N
b101 )
b101 M
b101 s
b101 H
b101 W
b100 4
b100 e
b100 m
b100 p
b0 .
b0 j
b0 x
b0 ~
b0 /
b0 J
b0 P
b0 S
b0 U
b0 [
b0 _
b0 w
#10
b0 2
b0 k
b0 !"
b101 F
b101 Q
b0 K
b0 N
#11
1c
0'
b0 G
b0 Y
b101 L
b101 V
#12
1"
#13
b101 ""
b100 !
b100 7
b100 a
#14
b1000 +
b1000 r
b1000 *
b1000 o
b1000 q
b1000 1
b1000 b
b1000 d
b1000 n
#15
b1001 ,
b1001 I
b1001 O
b1001 R
b1001 T
b1001 X
b1001 Z
b1001 ^
b1001 i
b100 (
b100 f
b100 }
b101101 \
b1 9
b1 v
b1 =
b1 t
b1001 g
b1 3
b1 {
b1 |
b1 z
b101 /
b101 J
b101 P
b101 S
b101 U
b101 [
b101 _
b101 w
b10000000000001001 #
b10000000000001001 &
#16
b1101 F
b1101 Q
b1001 )
b1001 M
b1001 s
b1001 H
b1001 W
b1 K
b1 N
0"
#17
b1100 4
b1100 e
b1100 m
b1100 p
b101101 G
b101101 Y
b1110 L
b1110 V
#20
1"
#21
b1001 #"
b1000 !
b1000 7
b1000 a
#22
b1100 +
b1100 r
b1100 *
b1100 o
b1100 q
b1100 1
b1100 b
b1100 d
b1100 n
